openzgy/__init__.py
openzgy/api.py
openzgy/exception.py
openzgy/iterator.py
openzgy/zgypublic.py
openzgy/impl/__init__.py
openzgy/impl/bulk.py
openzgy/impl/compress.py
openzgy/impl/enum.py
openzgy/impl/file.py
openzgy/impl/genlod.py
openzgy/impl/histogram.py
openzgy/impl/lodalgo.py
openzgy/impl/meta.py
openzgy/impl/stats.py
openzgy/impl/transform.py
openzgy/impl/zfp_compress.py
zgyio/__init__.py
zgyio/accessors.py
zgyio/loader.py
zgyio/open.py
zgyio/read.py
zgyio/tools.py
zgyio-0.0.4.dist-info/LICENSE.txt
zgyio-0.0.4.dist-info/METADATA
zgyio-0.0.4.dist-info/WHEEL
zgyio-0.0.4.dist-info/top_level.txt
zgyio-0.0.4.dist-info/RECORD
