Metadata-Version: 2.1
Name: zgyio
Version: 0.0.4
Summary: Convenience wrapper around OpenZGY Python implementation
Home-page: https://github.com/equinor/zgyio
Author: equinor
License: UNKNOWN
Platform: UNKNOWN
License-File: LICENSE.txt
Requires-Dist: numpy
Requires-Dist: segyio
